greenflare/__init__.py
greenflare/app.py
greenflare/greenflare.py
greenflare/core/__init__.py
greenflare/core/defaults.py
greenflare/core/gflarecrawler.py
greenflare/core/gflaredb.py
greenflare/core/gflareresponse.py
greenflare/core/gflarerobots.py
greenflare/resources/greenflare-icon-192x192.png
greenflare/resources/greenflare-icon-32x32.ico
greenflare/resources/greenflare-icon-32x32.png
greenflare/resources/greenflare-logo.svg
greenflare/widgets/__init__.py
greenflare/widgets/aboutwindow.py
greenflare/widgets/checkboxgroup.py
greenflare/widgets/crawltab.py
greenflare/widgets/enhancedentry.py
greenflare/widgets/exclusionstab.py
greenflare/widgets/extractionstab.py
greenflare/widgets/filterwindow.py
greenflare/widgets/helpers.py
greenflare/widgets/listcrawl.py
greenflare/widgets/menuhelper.py
greenflare/widgets/progresswindow.py
greenflare/widgets/settingstab.py
greenflare/widgets/updatewindow.py
greenflare/widgets/viewinlinks.py
greenflare/widgets/windowhelper.py
tests/__init__.py
tests/link-extraction-test.py
tests/request-url-test.py
tests/unit-tests.py
greenflare-0.98.1.dist-info/LICENSE
greenflare-0.98.1.dist-info/METADATA
greenflare-0.98.1.dist-info/WHEEL
greenflare-0.98.1.dist-info/entry_points.txt
greenflare-0.98.1.dist-info/top_level.txt
greenflare-0.98.1.dist-info/RECORD
