Metadata-Version: 2.1
Name: greenflare
Version: 0.98.1
Summary: SEO Web Crawler and Analysis Tool
Home-page: https://greenflare.io
Author: Benjamin Görler
Author-email: ben@greenflare.io
License: GPLv3+
Project-URL: Source, https://github.com/beb7/gflare-tk/
Project-URL: Tracker, https://github.com/beb7/gflare-tk/issues
Platform: UNKNOWN
Classifier: License :: OSI Approved :: GNU General Public License v3 or later (GPLv3+)
Classifier: Programming Language :: Python :: 3
Classifier: Programming Language :: Python :: 3.7
Classifier: Programming Language :: Python :: 3.8
Classifier: Programming Language :: Python :: 3.9
Classifier: Topic :: Internet :: WWW/HTTP
Classifier: Operating System :: OS Independent
Requires-Python: >=3.7
Requires-Dist: requests
Requires-Dist: lxml
Requires-Dist: cssselect
Requires-Dist: ua-parser
Requires-Dist: pillow
Requires-Dist: packaging
